sphinxnotes/comboroles/__init__.py
sphinxnotes_comboroles-1.0.dist-info/LICENSE
sphinxnotes_comboroles-1.0.dist-info/METADATA
sphinxnotes_comboroles-1.0.dist-info/WHEEL
sphinxnotes_comboroles-1.0.dist-info/top_level.txt
sphinxnotes_comboroles-1.0.dist-info/RECORD
