Metadata-Version: 2.1
Name: sphinxnotes-comboroles
Version: 1.0
Summary: Sphinx extension for composing multiple roles
Author: Shengyu Zhang
Maintainer: Shengyu Zhang
Project-URL: homepage, https://sphinx.silverrainz.me/comboroles
Project-URL: documentation, https://sphinx.silverrainz.me/comboroles
Project-URL: repository, https://github.com/sphinx-notes/comboroles
Project-URL: changelog, https://sphinx.silverrainz.me/comboroles/changelog.html
Project-URL: tracker, https://github.com/sphinx-notes/comboroles/issues
Keywords: sphinx,extension,documentation
Classifier: Environment :: Plugins
Classifier: Framework :: Sphinx
Classifier: Framework :: Sphinx :: Extension
Classifier: License :: OSI Approved :: BSD License
Classifier: Operating System :: OS Independent
Classifier: Programming Language :: Python
Classifier: Programming Language :: Python :: 3
Classifier: Topic :: Documentation
Classifier: Topic :: Documentation :: Sphinx
Requires-Python: >=3.8
License-File: LICENSE
Requires-Dist: Sphinx >=4
Provides-Extra: dev
Requires-Dist: build ; extra == 'dev'
Requires-Dist: twine ; extra == 'dev'
Requires-Dist: cruft ; extra == 'dev'
Provides-Extra: docs
Requires-Dist: furo ; extra == 'docs'
Requires-Dist: sphinxnotes-any ; extra == 'docs'
Requires-Dist: sphinx-design ; extra == 'docs'
Requires-Dist: sphinx-copybutton ; extra == 'docs'
Requires-Dist: sphinxcontrib-gtagjs ; extra == 'docs'
Requires-Dist: sphinxnotes-strike ; extra == 'docs'
Provides-Extra: test
Requires-Dist: pytest ; extra == 'test'
